{"nodes": [{"id": "preview_tags_component", "label": "Tags and Buttons Preview", "file_type": "document", "source_file": "temp/preview/tags.html", "source_location": null, "source_url": null, "captured_at": null, "author": null, "contributor": null}, {"id": "preview_tags_ow_status", "label": "Status Pill (.ow-status)", "file_type": "concept", "source_file": "temp/preview/tags.html", "source_location": null, "source_url": null, "captured_at": null, "author": null, "contributor": null}, {"id": "preview_tags_ow_tag", "label": "General Purpose Tag (.ow-tag)", "file_type": "concept", "source_file": "temp/preview/tags.html", "source_location": null, "source_url": null, "captured_at": null, "author": null, "contributor": null}, {"id": "preview_tags_ow_concept_tag", "label": "Concept Tag (.ow-concept-tag)", "file_type": "concept", "source_file": "temp/preview/tags.html", "source_location": null, "source_url": null, "captured_at": null, "author": null, "contributor": null}, {"id": "preview_tags_ow_code_chip", "label": "Code Criterion Chip (.ow-code-chip)", "file_type": "concept", "source_file": "temp/preview/tags.html", "source_location": null, "source_url": null, "captured_at": null, "author": null, "contributor": null}, {"id": "preview_tags_ow_btn_primary", "label": "Primary CTA Button (.ow-btn-primary)", "file_type": "concept", "source_file": "temp/preview/tags.html", "source_location": null, "source_url": null, "captured_at": null, "author": null, "contributor": null}, {"id": "preview_tags_ow_btn_solid", "label": "Solid Button (.ow-btn-solid)", "file_type": "concept", "source_file": "temp/preview/tags.html", "source_location": null, "source_url": null, "captured_at": null, "author": null, "contributor": null}, {"id": "preview_tags_ow_btn_outline", "label": "Outline Button (.ow-btn-outline)", "file_type": "concept", "source_file": "temp/preview/tags.html", "source_location": null, "source_url": null, "captured_at": null, "author": null, "contributor": null}, {"id": "preview_tags_ow_btn_ghost", "label": "Ghost Button (.ow-btn-ghost)", "file_type": "concept", "source_file": "temp/preview/tags.html", "source_location": null, "source_url": null, "captured_at": null, "author": null, "contributor": null}, {"id": "preview_tags_optical_centering", "label": "Optical Centering Primitive", "file_type": "concept", "source_file": "temp/preview/tags.html", "source_location": null, "source_url": null, "captured_at": null, "author": null, "contributor": null}, {"id": "design_token_components_css", "label": "components.css Component Primitives", "file_type": "document", "source_file": "temp/preview/tags.html", "source_location": null, "source_url": null, "captured_at": null, "author": null, "contributor": null}], "edges": [{"source": "preview_tags_component", "target": "design_token_colors_and_type_css", "relation": "references", "confidence": "EXTRACTED", "confidence_score": 1.0, "source_file": "temp/preview/tags.html", "source_location": "line 3", "weight": 1.0}, {"source": "preview_tags_component", "target": "design_token_components_css", "relation": "references", "confidence": "EXTRACTED", "confidence_score": 1.0, "source_file": "temp/preview/tags.html", "source_location": "line 4", "weight": 1.0}, {"source": "preview_tags_component", "target": "preview_tags_ow_status", "relation": "implements", "confidence": "EXTRACTED", "confidence_score": 1.0, "source_file": "temp/preview/tags.html", "source_location": "line 26", "weight": 1.0}, {"source": "preview_tags_component", "target": "preview_tags_ow_tag", "relation": "implements", "confidence": "EXTRACTED", "confidence_score": 1.0, "source_file": "temp/preview/tags.html", "source_location": "line 48", "weight": 1.0}, {"source": "preview_tags_component", "target": "preview_tags_ow_concept_tag", "relation": "implements", "confidence": "EXTRACTED", "confidence_score": 1.0, "source_file": "temp/preview/tags.html", "source_location": "line 57", "weight": 1.0}, {"source": "preview_tags_component", "target": "preview_tags_ow_code_chip", "relation": "implements", "confidence": "EXTRACTED", "confidence_score": 1.0, "source_file": "temp/preview/tags.html", "source_location": "line 69", "weight": 1.0}, {"source": "preview_tags_component", "target": "preview_tags_ow_btn_primary", "relation": "implements", "confidence": "EXTRACTED", "confidence_score": 1.0, "source_file": "temp/preview/tags.html", "source_location": "line 83", "weight": 1.0}, {"source": "preview_tags_component", "target": "preview_tags_ow_btn_solid", "relation": "implements", "confidence": "EXTRACTED", "confidence_score": 1.0, "source_file": "temp/preview/tags.html", "source_location": "line 84", "weight": 1.0}, {"source": "preview_tags_component", "target": "preview_tags_ow_btn_outline", "relation": "implements", "confidence": "EXTRACTED", "confidence_score": 1.0, "source_file": "temp/preview/tags.html", "source_location": "line 85", "weight": 1.0}, {"source": "preview_tags_component", "target": "preview_tags_ow_btn_ghost", "relation": "implements", "confidence": "EXTRACTED", "confidence_score": 1.0, "source_file": "temp/preview/tags.html", "source_location": "line 86", "weight": 1.0}, {"source": "preview_tags_ow_btn_primary", "target": "design_token_cyan700", "relation": "references", "confidence": "EXTRACTED", "confidence_score": 1.0, "source_file": "temp/preview/tags.html", "source_location": "line 88", "weight": 1.0}, {"source": "preview_tags_optical_centering", "target": "preview_tags_ow_status", "relation": "rationale_for", "confidence": "EXTRACTED", "confidence_score": 1.0, "source_file": "temp/preview/tags.html", "source_location": "line 22", "weight": 1.0}, {"source": "preview_tags_optical_centering", "target": "preview_tags_ow_btn_primary", "relation": "rationale_for", "confidence": "EXTRACTED", "confidence_score": 1.0, "source_file": "temp/preview/tags.html", "source_location": "line 22", "weight": 1.0}, {"source": "preview_tags_ow_concept_tag", "target": "preview_table_well_strategy_table", "relation": "references", "confidence": "INFERRED", "confidence_score": 0.85, "source_file": "temp/preview/tags.html", "source_location": "line 57", "weight": 0.85}, {"source": "preview_tags_ow_code_chip", "target": "preview_table_well_strategy_table", "relation": "references", "confidence": "INFERRED", "confidence_score": 0.85, "source_file": "temp/preview/tags.html", "source_location": "line 69", "weight": 0.85}], "hyperedges": [{"id": "button_component_variants", "label": "Button Component Variants", "nodes": ["preview_tags_ow_btn_primary", "preview_tags_ow_btn_solid", "preview_tags_ow_btn_outline", "preview_tags_ow_btn_ghost"], "relation": "form", "confidence": "EXTRACTED", "confidence_score": 1.0, "source_file": "temp/preview/tags.html"}, {"id": "tag_and_chip_variants", "label": "Tag and Chip Component Variants", "nodes": ["preview_tags_ow_status", "preview_tags_ow_tag", "preview_tags_ow_concept_tag", "preview_tags_ow_code_chip"], "relation": "form", "confidence": "EXTRACTED", "confidence_score": 1.0, "source_file": "temp/preview/tags.html"}]}